{
  "id": "ip-002-doomsday-diary-en-drama",
  "title": "नाटक: 末日百日计划：人类最后的生存日志",
  "author": "[hi] AI Factory",
  "tags": [
    "[hi] 末日",
    "[hi] 重生",
    "[hi] 囤货",
    "[hi] 系统",
    "नाटक Adaptation"
  ],
  "description": "[hi] Adapted from novel: 陈峰在末世挣扎求生十年，最终惨死。醒来后发现自己回到了末日爆发前的一百天。带着前世的记忆和觉醒的空间系统，他开始疯狂筹集资金，囤积物资，加固房屋。当末日降临，别人在丧尸口中求生，他在避难所里吃火锅。",
  "createdAt": "2025-11-28T02:33:54.302Z",
  "status": "[hi] completed",
  "sourceNovelId": "[hi] ip-002-doomsday-diary-en-novel",
  "language": "hi"
}