{
  "id": "daily-ip-1764283990553-it-drama",
  "title": "Dramma: Romanzo: A new daily IP conce...",
  "author": "[it] AI Factory",
  "tags": [
    "[it] [it] Cultivation",
    "[it] [it] Immortality",
    "[it] [it] System",
    "[it] [it] romance_revenge",
    "Dramma Adaptation"
  ],
  "description": "[it] Adapted from novel: [it] A new daily IP concept generated at 2025-11-27T22:53:10.553Z",
  "createdAt": "2025-11-28T02:33:43.202Z",
  "status": "[it] completed",
  "sourceNovelId": "[it] daily-ip-1764283990553-it-novel",
  "language": "it"
}