{
  "id": "sample-ip-v5-global-de-drama",
  "title": "[es] Drama: Roman: A story about a glob...",
  "author": "[es] AI Factory",
  "tags": [
    "[es] [de] Cultivation",
    "[es] [de] Immortality",
    "[es] [de] System",
    "[es] [de] romance_revenge",
    "[es] Drama Adaptation"
  ],
  "description": "[es] Adapted from novel: [de] A story about a global trade empire connecting cultures.",
  "createdAt": "2025-11-28T02:34:31.963Z",
  "status": "[es] completed",
  "sourceNovelId": "[es] sample-ip-v5-global-de-novel",
  "language": "es"
}