{
  "ipId": "sample-ip-global",
  "idea": "[hi] A global sci-fi epic about a unified earth.",
  "genre": "[hi] romance_revenge",
  "language": "hi",
  "novelId": "sample-ip-global-novel-hi",
  "dramaId": "sample-ip-global-drama-hi",
  "comicId": "sample-ip-global-comic-hi",
  "createdAt": "2025-11-27T21:46:10.485Z",
  "novelMetadata": {
    "id": "sample-ip-global-novel",
    "title": "उपन्यास: A global sci-fi epic...",
    "author": "[hi] AI Factory",
    "genre": "[hi] romance_revenge",
    "tags": [
      "[hi] Cultivation",
      "[hi] Immortality",
      "[hi] System",
      "[hi] romance_revenge"
    ],
    "description": "[hi] A global sci-fi epic about a unified earth.",
    "characters": [
      "[hi] Li Wei",
      "[hi] Fairy Chen",
      "[hi] Elder Zhang"
    ],
    "createdAt": "2025-11-27T21:46:09.954Z",
    "status": "[hi] completed",
    "language": "[hi] zh"
  },
  "dramaMetadata": {
    "id": "sample-ip-global-drama",
    "title": "नाटक: उपन्यास: A global sci-fi epic...",
    "author": "[hi] AI Factory",
    "tags": [
      "[hi] Cultivation",
      "[hi] Immortality",
      "[hi] System",
      "[hi] romance_revenge",
      "नाटक Adaptation"
    ],
    "description": "[hi] Adapted from novel: A global sci-fi epic about a unified earth.",
    "createdAt": "2025-11-27T21:46:10.206Z",
    "status": "[hi] completed",
    "sourceNovelId": "[hi] sample-ip-global-novel"
  },
  "comicMetadata": {
    "id": "sample-ip-global-comic",
    "title": "कॉमिक: उपन्यास: A global sci-fi epic...",
    "author": "[hi] AI Artist",
    "genre": "[hi] romance_revenge",
    "description": "[hi] Adapted from novel: A global sci-fi epic about a unified earth.",
    "status": "[hi] ongoing",
    "createdAt": "2025-11-27T21:46:10.362Z",
    "sourceNovelId": "[hi] sample-ip-global-novel"
  }
}