{
  "ipId": "ip-005-infinite-upgrade",
  "idea": "穿越异界获得无限升级系统，杀怪升级，装备全靠爆，从此横推无敌。",
  "genre": "fantasy_system",
  "language": "zh",
  "novelId": "ip-005-infinite-upgrade-novel",
  "dramaId": "ip-005-infinite-upgrade-drama",
  "comicId": "ip-005-infinite-upgrade-comic",
  "createdAt": "2025-11-28T01:52:06.273Z",
  "novelMetadata": {
    "id": "ip-005-infinite-upgrade-novel",
    "title": "无限升级系统：开局无敌",
    "author": "AI Factory",
    "genre": "fantasy_system",
    "tags": [
      "玄幻",
      "系统",
      "无敌流",
      "热血"
    ],
    "description": "叶天穿越到以武为尊的玄幻世界，觉醒了无限升级系统。只要击杀敌人或妖兽，就能获得经验值和神级装备。从此，他一路高歌猛进，拳打天才，脚踢老怪，探秘境，夺异火，成就无上武帝。",
    "characters": [
      "叶天",
      "慕容雪"
    ],
    "createdAt": "2025-11-28T01:52:05.922Z",
    "status": "completed",
    "language": "zh",
    "world_setting": "宏大的玄幻世界，宗门林立，强者为尊",
    "core_theme": "莫欺少年穷，我命由我不由天",
    "short_drama_style": "特效炸裂，打斗精彩，节奏超快",
    "comic_style": "热血少年漫，日漫风格",
    "game_mode": "rpg"
  },
  "dramaMetadata": {
    "id": "ip-005-infinite-upgrade-drama",
    "title": "Drama: 无限升级系统：开局无敌",
    "author": "AI Factory",
    "tags": [
      "玄幻",
      "系统",
      "无敌流",
      "热血",
      "Drama Adaptation"
    ],
    "description": "Adapted from novel: 叶天穿越到以武为尊的玄幻世界，觉醒了无限升级系统。只要击杀敌人或妖兽，就能获得经验值和神级装备。从此，他一路高歌猛进，拳打天才，脚踢老怪，探秘境，夺异火，成就无上武帝。",
    "createdAt": "2025-11-28T01:52:05.940Z",
    "status": "completed",
    "sourceNovelId": "ip-005-infinite-upgrade-novel"
  },
  "comicMetadata": {
    "id": "ip-005-infinite-upgrade-comic",
    "title": "Comic: 无限升级系统：开局无敌",
    "author": "AI Artist",
    "genre": "fantasy_system",
    "description": "Adapted from novel: 叶天穿越到以武为尊的玄幻世界，觉醒了无限升级系统。只要击杀敌人或妖兽，就能获得经验值和神级装备。从此，他一路高歌猛进，拳打天才，脚踢老怪，探秘境，夺异火，成就无上武帝。",
    "status": "ongoing",
    "createdAt": "2025-11-28T01:52:06.100Z",
    "sourceNovelId": "ip-005-infinite-upgrade-novel"
  },
  "games": [
    {
      "gameId": "ip-005-infinite-upgrade-if-zh",
      "mode": "if",
      "language": "zh"
    },
    {
      "gameId": "ip-005-infinite-upgrade-vn-zh",
      "mode": "vn",
      "language": "zh"
    }
  ]
}